odsclient/__init__.py
odsclient/_version.py
odsclient/core.py
odsclient/keyring_cmds.py
odsclient/py.typed
odsclient/shortcuts.py
odsclient/utils.py
odsclient-0.8.4.dist-info/LICENSE
odsclient-0.8.4.dist-info/METADATA
odsclient-0.8.4.dist-info/WHEEL
odsclient-0.8.4.dist-info/entry_points.txt
odsclient-0.8.4.dist-info/top_level.txt
odsclient-0.8.4.dist-info/RECORD
