Metadata-Version: 2.1
Name: odsclient
Version: 0.8.4
Summary: A nonofficial client for OpenDataSoft API.
Home-page: https://github.com/smarie/python-odsclient
Author: Sylvain MARIE <sylvain.marie@se.com>
Maintainer: Sylvain MARIE <sylvain.marie@se.com>
License: BSD 3-Clause
Download-URL: https://github.com/smarie/python-odsclient/tarball/0.8.4
Keywords: OpenDataSoft open data soft ods client API dataset download csv json cache
Platform: UNKNOWN
Classifier: Development Status :: 5 - Production/Stable
Classifier: Intended Audience :: Developers
Classifier: License :: OSI Approved :: BSD License
Classifier: Topic :: Software Development :: Libraries :: Python Modules
Classifier: Programming Language :: Python
Classifier: Programming Language :: Python :: 2
Classifier: Programming Language :: Python :: 2.7
Classifier: Programming Language :: Python :: 3
Classifier: Programming Language :: Python :: 3.5
Classifier: Programming Language :: Python :: 3.6
Classifier: Programming Language :: Python :: 3.7
Classifier: Programming Language :: Python :: 3.8
Classifier: Programming Language :: Python :: 3.9
License-File: LICENSE
Requires-Dist: requests
Requires-Dist: pathlib2 ; python_version < "3.2"
Provides-Extra: full
Requires-Dist: keyring ; extra == 'full'
Requires-Dist: click ; extra == 'full'
Requires-Dist: tqdm ; extra == 'full'
